{
  "title_bn": "বিষাদ সিন্ধু",
  "title_en": "Bishad Sindhu (The Ocean of Sorrow)",
  "author_bn": "মীর মশাররফ হোসেন",
  "author_en": "Mir Mosharraf Hossain",
  "author_slug": "mir-mosharraf-hossain",
  "year": "1885",
  "published_date": "2026-03-10",
  "status": "published",
  "category": "Novel",
  "description_en": "Bishad Sindhu is a historical novel by Mir Mosharraf Hossain, considered one of the greatest works in Bengali literature. It narrates the tragedy of Karbala and the martyrdom of Imam Husayn ibn Ali.",
  "description_bn": "বিষাদ সিন্ধু মীর মশাররফ হোসেনের ঐতিহাসিক উপন্যাস, যা কারবালার ট্র্যাজেডি ও ইমাম হুসাইনের শাহাদতের কাহিনী বর্ণনা করে।",
  "original_publisher": "Self-published",
  "source": "Public domain",
  "cover_image": "/bangla-library/covers/bishad-sindhu.jpg",
  "paragraphs": [
    {
      "id": 1,
      "bn": "মহরম মাসের দশম দিন। কারবালার প্রান্তরে ফোরাতের তীরে ইমাম হোসেনের শিবির।",
      "en": "The tenth day of Muharram. On the plains of Karbala, beside the Euphrates, stands the camp of Imam Husayn."
    },
    {
      "id": 2,
      "bn": "সূর্য উদিত হইয়াছে, কিন্তু আজ তাহার আলো যেন ম্লান। আকাশ নীল, কিন্তু হৃদয় ভারাক্রান্ত।",
      "en": "The sun has risen, yet today its light seems dim. The sky is blue, but all hearts are heavy with grief."
    },
    {
      "id": 3,
      "bn": "ইমাম হোসেন তাঁবুর বাহিরে দাঁড়াইয়া আছেন। তাঁহার মুখমণ্ডলে প্রশান্তির ছায়া, কিন্তু চোখে অশ্রু।",
      "en": "Imam Husayn stands outside his tent. On his face is the shadow of serenity, but tears glisten in his eyes."
    },
    {
      "id": 4,
      "bn": "শিবিরে শিশুরা পিপাসায় কাঁদিতেছে। নারীরা চুপ করিয়া আছেন, কারণ কান্নার আর শক্তি নাই।",
      "en": "In the camp, children weep with thirst. The women are silent, for they have no strength left even for tears."
    },
    {
      "id": 5,
      "bn": "ইয়াজিদের বিশাল বাহিনী চারদিক ঘেরিয়া আছে। কিন্তু হোসেন অবিচল, সত্যের পথে তিনি অটল।",
      "en": "Yazid's vast army surrounds them on all sides. Yet Husayn remains unmoved, steadfast on the path of truth."
    },
    {
      "id": 6,
      "bn": "আব্বাস ঘোড়া লইয়া প্রস্তুত। ফোরাত থেকে জল আনিতে যাইবেন, শিশুদের পিপাসা মেটাইতে।",
      "en": "Abbas stands ready with his horse. He will go to the Euphrates for water, to quench the thirst of the children."
    },
    {
      "id": 7,
      "bn": "যুদ্ধ শুরু হইল। একে একে সাথীরা শহীদ হইতে লাগিলেন। হোসেন দেখিলেন, একা হইয়া যাইতেছেন।",
      "en": "The battle began. One by one, his companions fell as martyrs. Husayn saw that he was becoming alone."
    },
    {
      "id": 8,
      "bn": "সন্ধ্যার আগেই সব শেষ হইয়া গেল। কারবালার মাটি রক্তে রঞ্জিত হইল।",
      "en": "Before evening, all was over. The soil of Karbala was dyed crimson with blood."
    },
    {
      "id": 9,
      "bn": "ইতিহাস সাক্ষী, এই দিনে সত্য মিথ্যার কাছে পরাজিত হয় নাই — বরং অমর হইয়াছে।",
      "en": "History bears witness: on this day, truth was not defeated by falsehood — rather, it became immortal."
    },
    {
      "id": 10,
      "bn": "কারবালার কাহিনী শেষ হয় না। প্রতি বছর মহরমে এই বেদনা নতুন করিয়া জাগিয়া ওঠে।",
      "en": "The story of Karbala never ends. Each year at Muharram, this sorrow awakens anew."
    }
  ]
}
